python_cobol/__init__.py
python_cobol/python_cobol.py
python_cobol-0.1.4.dist-info/METADATA
python_cobol-0.1.4.dist-info/WHEEL
python_cobol-0.1.4.dist-info/top_level.txt
python_cobol-0.1.4.dist-info/RECORD
